awsclient/__init__.py
awsclient/__main__.py
awsclient/config.py
awsclient/ec2.py
awsclient/s3.py
awsclient/sqs.py
awsclient/sshclient.py
awsconnect-1.3.1.dist-info/LICENSE
awsconnect-1.3.1.dist-info/METADATA
awsconnect-1.3.1.dist-info/WHEEL
awsconnect-1.3.1.dist-info/entry_points.txt
awsconnect-1.3.1.dist-info/top_level.txt
awsconnect-1.3.1.dist-info/RECORD
