Metadata-Version: 2.1
Name: awsconnect
Version: 1.3.1
Summary: Easy connect to AWS and gather info about EC2, S3, SQS
Home-page: https://github.com/zakharb/awsconnect
Classifier: Programming Language :: Python :: 3
Classifier: License :: OSI Approved :: GNU General Public License v3 (GPLv3)
Classifier: Intended Audience :: Developers
Requires-Python: >=3.6
License-File: LICENSE
